.editorconfig
.gitignore
.pre-commit-config.yaml
.soliumignore
.soliumrc.json
.travis.yml
CHANGELOG.rst
Dockerfile
LICENSE
MANIFEST.in
README.rst
constraints.txt
project.json
requirements.txt
setup.cfg
setup.py
.travis/push-docker-image.sh
/home/travis/build/trustlines-network/contracts/contracts/CurrencyNetwork.sol
/home/travis/build/trustlines-network/contracts/contracts/CurrencyNetworkInterface.sol
/home/travis/build/trustlines-network/contracts/contracts/Exchange.sol
/home/travis/build/trustlines-network/contracts/contracts/lib/Authorizable.sol
/home/travis/build/trustlines-network/contracts/contracts/lib/Destructable.sol
/home/travis/build/trustlines-network/contracts/contracts/lib/ECVerify.sol
/home/travis/build/trustlines-network/contracts/contracts/lib/EtherRouter.sol
/home/travis/build/trustlines-network/contracts/contracts/lib/Ownable.sol
/home/travis/build/trustlines-network/contracts/contracts/lib/Resolver.sol
/home/travis/build/trustlines-network/contracts/contracts/lib/SafeMath.sol
/home/travis/build/trustlines-network/contracts/contracts/lib/it_set_lib.sol
/home/travis/build/trustlines-network/contracts/contracts/tokens/DummyToken.sol
/home/travis/build/trustlines-network/contracts/contracts/tokens/Receiver_Interface.sol
/home/travis/build/trustlines-network/contracts/contracts/tokens/StandardToken.sol
/home/travis/build/trustlines-network/contracts/contracts/tokens/Token.sol
/home/travis/build/trustlines-network/contracts/contracts/tokens/UnwETH.sol
contracts/CurrencyNetwork.sol
contracts/CurrencyNetworkInterface.sol
contracts/Exchange.sol
contracts/lib/Authorizable.sol
contracts/lib/Destructable.sol
contracts/lib/ECVerify.sol
contracts/lib/EtherRouter.sol
contracts/lib/Ownable.sol
contracts/lib/Resolver.sol
contracts/lib/SafeMath.sol
contracts/lib/it_set_lib.sol
contracts/tokens/DummyToken.sol
contracts/tokens/Receiver_Interface.sol
contracts/tokens/StandardToken.sol
contracts/tokens/Token.sol
contracts/tokens/UnwETH.sol
docs/deploy.md
trustlines_contracts.egg-info/PKG-INFO
trustlines_contracts.egg-info/SOURCES.txt
trustlines_contracts.egg-info/dependency_links.txt
trustlines_contracts.egg-info/entry_points.txt
trustlines_contracts.egg-info/requires.txt
trustlines_contracts.egg-info/top_level.txt