Metadata-Version: 1.2
Name: trustlines-contracts
Version: 0.1.3
Summary: Smart Contracts for Trustlines-Network
Home-page: https://github.com/trustlines-network/contracts
Author: Trustlines-Network
Author-email: 
License: MIT
Keywords: trustlines
Platform: UNKNOWN
Classifier: Development Status :: 2 - Pre-Alpha
Classifier: Intended Audience :: Developers
Classifier: License :: OSI Approved :: MIT License
Classifier: Programming Language :: Python :: 3
Classifier: Programming Language :: Python :: 3.5
Classifier: Programming Language :: Python :: 3.6
Requires-Python: >=3
